DTSR-0.1.1.dist-info/METADATA
DTSR-0.1.1.dist-info/RECORD
DTSR-0.1.1.dist-info/WHEEL
DTSR-0.1.1.dist-info/top_level.txt
dtsr/__init__.py
dtsr/baselines.py
dtsr/config.py
dtsr/data.py
dtsr/dtsr.py
dtsr/dtsrbayes.py
dtsr/dtsrmle.py
dtsr/formula.py
dtsr/io.py
dtsr/kwargs.py
dtsr/plot.py
dtsr/signif.py
dtsr/sphinx.py
dtsr/util.py
dtsr/bin/__init__.py
dtsr/bin/compare.py
dtsr/bin/compare_spillover.py
dtsr/bin/convolve.py
dtsr/bin/get_table_betas.py
dtsr/bin/get_table_compare_dtsr.py
dtsr/bin/get_table_dtsr_v_baselines.py
dtsr/bin/help.py
dtsr/bin/optimize_spillover.py
dtsr/bin/partition.py
dtsr/bin/plot.py
dtsr/bin/plot_baseline_spillover_estimates.py
dtsr/bin/pool_compare.py
dtsr/bin/predict.py
dtsr/bin/repickle.py
dtsr/bin/summary.py
dtsr/bin/synth.py
dtsr/bin/train.py
