Metadata-Version: 2.1
Name: DTSR
Version: 0.1.1
Summary: A toolkit for Deconvolutional Time Series Regression (DTSR)
Home-page: https://github.com/coryshain/dtsr
Author: Cory Shain
Author-email: cory.shain@gmail.com
License: UNKNOWN
Platform: UNKNOWN
Requires-Dist: numpy (>=1.9.1)
Requires-Dist: pandas (>=0.19.2)
Requires-Dist: matplotlib
Requires-Dist: tensorflow (>=1.3.0)
Requires-Dist: scipy (>=0.14)
